kitaevmodel/__init__.py
kitaevmodel/basesample.py
kitaevmodel/eigenstates.py
kitaevmodel/hamiltonian_creator.py
kitaevmodel/image_generator.py
kitaevmodel/shapes.py
kitaevmodel/time_evolution.py
kitaevmodel/tests/__init__.py
kitaevmodel/tests/kitaevmodel_tests.py
kitaevmodel-0.1.2.dist-info/METADATA
kitaevmodel-0.1.2.dist-info/WHEEL
kitaevmodel-0.1.2.dist-info/top_level.txt
kitaevmodel-0.1.2.dist-info/RECORD
