Metadata-Version: 2.1
Name: kitaevmodel
Version: 0.1.2
Summary: A tool for numerical simulation of Kitaev honeycomb model
Author: Igor Timoshuk
Author-email: <iltimoshuk@gmail.com>
Keywords: python,Kitaev model
Classifier: Development Status :: 3 - Alpha
Classifier: Intended Audience :: Education
Classifier: Programming Language :: Python :: 3
Classifier: Operating System :: MacOS :: MacOS X
Classifier: Operating System :: Microsoft :: Windows
Requires-Dist: numpy
Requires-Dist: tensorflow
Requires-Dist: networkx
Requires-Dist: matplotlib
Requires-Dist: scipy
Requires-Dist: sympy
